{
    "no_wrap": true,
    "title": "日本C结束后・Noise",
    "text_block_list": [
        {
            "name": "空中神宫的纪录",
            "text": "/*宿命根本没有改变。"
        },
        {
            "name": "空中神宫的纪录",
            "text": "我明明赢了，可是……\n好歌剧和怒涛连在比赛中都能变强，\n甚至超越了理论值。",
            "color_text_info_list": [
                "好歌剧",
                "怒涛"
            ]
        },
        {
            "name": "空中神宫的纪录",
            "text": "纵使在三冠路线留下成果，大家还是拿我\n跟上个世代比较，或认为我缺乏对手……\n种种原因下，我被烙上了“最弱世代”的称号──"
        },
        {
            "name": "空中神宫的纪录",
            "text": "……“Parcae”的错误突然修复了。\n原本已经克服的“最糟宿命”再次降临。"
        },
        {
            "name": "空中神宫的纪录",
            "text": "根据“Parcae”显示的计算结果，\n在下一个目标“天皇赏（春）”，\n我将会败北。*/"
        }
    ]
}