{
    "no_wrap": true,
    "title": "樱花赏结束后・只属于我的dream",
    "text_block_list": [
        {
            "name": "采珠",
            "text": "Amazing！感觉跑得很棒！\n英里赛果然是我的best呢！"
        },
        {
            "name": "采珠",
            "text": "下一个目标是1600米的“NHK英里C”？\n但真的可以放弃2400米的“橡树大赛”吗？\n欧洲最大的GⅠ是2400米吧……",
            "color_text_info_list": [
                "NHK英里C"
            ]
        },
        {
            "name": "采珠",
            "text": "──不对，放弃2400米吧。\n我最大的目标是“欧洲GⅠ胜利”。\n我想向世界展现的是勇气，而不是无谋。"
        },
        {
            "name": "采珠",
            "text": "为了彻底发挥可能性，我要靠英里赛挑战世界！\n下一个目标是最适合我的“NHK英里C”！"
        }
    ]
}