{
    "no_wrap": true,
    "title": "NHK英里C结束后・约定的顶点",
    "text_block_list": [
        {
            "name": "采珠",
            "text": "漂亮获胜！为热烈的喝采献上thanks！\n我一定会在欧洲，掀起和今天一样的喝采声！"
        },
        {
            "name": "采珠",
            "text": "我接下来要参加1800米的“玫瑰S”！\n你问为什么？因为欧洲英里赛赛道的草比较茂密，\n所以必须要有充裕的持久力！",
            "color_text_info_list": [
                "玫瑰S"
            ]
        },
        {
            "name": "采珠",
            "text": "“玫瑰S”之后，是2000米的“秋华赏”！\n然后明年进军世界！我要走的road已经决定好了！",
            "color_text_info_list": [
                "秋华赏"
            ]
        }
    ]
}