{
    "text_block_list": [
        {
            "name": "勇敢之心",
            "text": "莱茵，happy birthday!\n话不多说，我们有礼物要送你！\n会是什么呢？来猜猜看！"
        },
        {
            "name": "莱茵力量",
            "text": "诶诶！猜、猜不出来……！\n嗯~生日，生日……\n啊，总之先猜个蛋糕！？"
        },
        {
            "name": "勇敢之心",
            "text": "Wrong!\n是有蛋糕，不过礼物是别的哦。"
        },
        {
            "name": "空中救主",
            "text": "我们认真考虑了能帮上莱茵同学的东西。\n以平时的举止、习惯、言行等作为参考——"
        },
        {
            "name": "空中救主",
            "text": "得出的结果是，\n『晒太阳用品』。"
        },
        {
            "name": "莱茵力量",
            "text": "诶！？\n我确实喜欢晒太阳没错……用品吗？"
        },
        {
            "name": "空中救主",
            "text": "以前莱茵同学晒太阳时\n会因为太舒服不知不觉睡着吧。"
        },
        {
            "name": "勇敢之心",
            "text": "而且还会流口水，被虫子咬……\n呵呵，真是毫无防备呢！"
        },
        {
            "name": "莱茵力量",
            "text": "！？\n为、为什么会知道！？"
        },
        {
            "name": "勇敢之心",
            "text": "收集对手情报我可从不懈怠♪\n总之，枕头和毯子都要用起来！\n这可是方便携带的好东西哦！"
        },
        {
            "name": "空中救主",
            "text": "然后就是花露水。\n这个有驱虫效果，可以让你不受瘙痒困扰哦。"
        },
        {
            "name": "莱茵力量",
            "text": "诶诶~~！？ 这样我会睡得更沉吧！\n不过谢谢你们~~~~~~！！"
        }
    ]
}