{
    "no_wrap": true,
    "title": "参赛的疲劳",
    "text_block_list": [
        {
            "name": "独白",
            "text": "竞赛结束后……\n东海帝王深深地叹了口气。"
        },
        {
            "name": "东海帝王",
            "text": "嗳～训练员！\n我的肚子饿扁了！"
        },
        {
            "name": "东海帝王",
            "text": "现在就想吃香煎雪地胡萝卜，\n还想喝无添加的胡萝卜汁～！",
            "choice_data_list": [
                "现在就要有点强人所难……"
            ]
        },
        {
            "name": "东海帝王",
            "text": "咦～！讨厌讨厌！我肚子饿了，\n你快想想办法～！！"
        },
        {
            "name": "东海帝王",
            "text": "而・且～～～～！！"
        },
        {
            "name": "东海帝王",
            "text": "我都这么努力了，\n再多夸几句嘛～！！"
        },
        {
            "name": "独白",
            "text": "东海帝王不断地耍任性。\n看来她似乎相当疲劳。\n或许该重新调整今后的参赛计划。"
        }
    ]
}