{
    "no_wrap": true,
    "title": "结局（普通）",
    "text_block_list": [
        {
            "name": "独白",
            "text": "东商变革漂亮地\n在这三年中取得了出色的成绩。"
        },
        {
            "name": "独白",
            "text": "我刚认识她时，\n她还是个任性的少女──"
        },
        {
            "name": "东商变革",
            "text": "使魔～～！"
        },
        {
            "name": "东商变革",
            "text": "使魔，你怎么还在房间里！\n我有说过今天要尝试新的魔法吧！"
        },
        {
            "name": "独白",
            "text": "──她还是一样叫我使魔，\n持续过着任性妄为的日子。",
            "choice_data_list": [
                "抱歉，我在整理比赛的资料……"
            ]
        },
        {
            "name": "东商变革",
            "text": "啥！？你也太散漫了～"
        },
        {
            "name": "东商变革",
            "text": "唉～算了。\n你乖乖待着别动。\n……真是的。"
        },
        {
            "name": "东商变革",
            "text": "湖畔☆魔女・兰花！\n使魔啊──变得无敌所向吧！",
            "choice_data_list": [
                "我变无敌了！？",
                "我变无敌了！？"
            ]
        },
        {
            "name": "东商变革",
            "text": "哼哼♪虽然只是试用看看，\n但看来是成功了。"
        },
        {
            "name": "东商变革",
            "text": "你现在拥有最强的身体，\n内心也变得非常坚强喔。"
        },
        {
            "name": "东商变革",
            "text": "赶紧来测试效果吧！",
            "choice_data_list": [
                "咦？"
            ]
        },
        {
            "name": "东商变革",
            "text": "哼哼，天才魔女Sweepy的魔法\n是完美无缺的。\n我要上啰！",
            "choice_data_list": [
                "等、等等！！"
            ]
        },
        {
            "name": "独白",
            "text": "我闭上眼睛，做好挨打的觉悟。\n希望至少不用住院──"
        },
        {
            "name": "独白",
            "text": "（……啪嚓）",
            "choice_data_list": [
                "……快门声？"
            ]
        },
        {
            "name": "东商变革",
            "text": "……笨蛋。被这东西打中感觉就很痛，\n我怎么可能拿来打你。"
        },
        {
            "name": "东商变革",
            "text": "刚才是在惩罚你\n因为工作而忘了和我的约定。\n下次再这样就不原谅你啰！"
        },
        {
            "name": "东商变革",
            "text": "呵呵，不过使魔拼命闭紧眼睛的照片……\n呵呵，超逊的……",
            "choice_data_list": [
                "请、请你删掉……",
                "请、请你删掉……"
            ]
        },
        {
            "name": "东商变革",
            "text": "我才不要～♪\n呵呵呵。"
        },
        {
            "name": "东商变革",
            "text": "使魔真的很笨耶。\n我怎么可能对你施展最强的魔法。"
        },
        {
            "name": "东商变革",
            "text": "……为什么你会不懂呢？\n你根本就不需要那种魔法。"
        }
    ]
}