{
    "no_wrap": true,
    "title": "你、我，还有『爱』",
    "text_block_list": [
        {
            "name": "独白",
            "text": "顺便外出的时候，来到了据说正在举办有点不一样的庙会的神社——\n然而。"
        },
        {
            "name": "独白",
            "text": "（——嘎、嘎……）",
            "choice_data_list": [
                "——什么都没有！？"
            ]
        },
        {
            "name": "唯独爱你",
            "text": "咦咦？　怎么会呢。\n明明地点是对的啊……"
        },
        {
            "name": "独白",
            "text": "……是我调查失误了。\n庙会好像昨天就结束了……",
            "choice_data_list": [
                "真的很对不起……"
            ]
        },
        {
            "name": "唯独爱你",
            "text": "——呵呵，不用那么垂头丧气的啦，训练员君！"
        },
        {
            "name": "唯独爱你",
            "text": "——呵呵，不用那么垂头丧气的啦，训练员酱！"
        },
        {
            "name": "唯独爱你",
            "text": "不过，既然都来了，不如在等车之前去散散步吧？",
            "choice_data_list": [
                "那可能要散步五个小时左右……"
            ]
        },
        {
            "name": "唯独爱你",
            "text": "嗯——……虽然那样也不错，\n但两个人一起走到火车站也挺好的。\n如果累了我可以背你哦！　怎么样？"
        },
        {
            "name": "唯独爱你",
            "text": "好悠闲啊～……空气好清新，\n感觉很神圣……"
        },
        {
            "name": "唯独爱你",
            "text": "啊。那边有灯笼！　是不是昨天庙会的遗留呢？　有点残缺之美的感觉♡",
            "choice_data_list": [
                "……其实还是想看看庙会"
            ]
        },
        {
            "name": "唯独爱你",
            "text": "当然我也很感兴趣，\n不过也不是只有这一次机会嘛。\n下次有机会我们再一起来吧。"
        },
        {
            "name": "唯独爱你",
            "text": "今天天气真好～。\n啊，你看！　发现了一朵心形的云！",
            "choice_data_list": [
                "呼、哈……嗯、嗯……！"
            ]
        },
        {
            "name": "唯独爱你",
            "text": "没关系吗？　我们再慢一点走吧。"
        },
        {
            "name": "唯独爱你",
            "text": "啊，那边是不是有个长椅？\n走到那里，休息一下吧！"
        },
        {
            "name": "唯独爱你",
            "text": "到车站……大概还有一半的路程。\n我们慢慢走吧♪"
        },
        {
            "name": "独白",
            "text": "坐在长椅上休息时，满心都是愧疚。\n因为我浪费了她宝贵的时间……",
            "choice_data_list": [
                "真的很抱歉……"
            ]
        },
        {
            "name": "唯独爱你",
            "text": "——为什么要道歉呢？"
        },
        {
            "name": "唯独爱你",
            "text": "其实根本没什么可道歉的哦。\n因为……现在我很幸福啊。",
            "choice_data_list": [
                "诶——"
            ]
        },
        {
            "name": "唯独爱你",
            "text": "呵呵。\n这条路真的什么都没有对吧。"
        },
        {
            "name": "唯独爱你",
            "text": "一路上真的超级长，\n只有一望无际的稻田绿和蔚蓝的天空。\n神社也只是很普通很朴素的地方。"
        },
        {
            "name": "唯独爱你",
            "text": "不过……就算是这种平淡无奇的风景，\n也有许多值得喜爱的地方哦。"
        },
        {
            "name": "唯独爱你",
            "text": "风吹着很舒服，青草的香味，\n云在天上缓缓流动让人很治愈——"
        },
        {
            "name": "唯独爱你",
            "text": "这些细微、质朴的小感动，\n能和训练员君一起体会。\n……光是这样，我就很幸福了。"
        },
        {
            "name": "唯独爱你",
            "text": "这些细微、质朴的小感动，\n能和训练员酱一起体会。\n……光是这样，我就很幸福了。"
        },
        {
            "name": "唯独爱你",
            "text": "和有『爱』的人一起度过，\n看似平淡无奇的时光——\n才是最奢侈、最充实的，不是吗？"
        },
        {
            "name": "独白",
            "text": "和她一起度过这平凡的时光，\n幸福、充实——她的话让我豁然开朗，\n心里一下子轻松了起来。",
            "choice_data_list": [
                "嗯……现在我真的很幸福"
            ]
        },
        {
            "name": "唯独爱你",
            "text": "——呵呵。差不多该出发了。"
        },
        {
            "name": "唯独爱你",
            "text": "只要和训练员君在一起，\n脚步都会变得轻快。\n所以什么时候都可以让我背你哦！",
            "choice_data_list": [
                "不，我也觉得脚步变轻了！",
                "嗯，我也觉得脚步变轻了！"
            ]
        },
        {
            "name": "唯独爱你",
            "text": "只要和训练员酱在一起，\n脚步都会变得轻快。\n所以什么时候都可以让我背你哦！",
            "choice_data_list": [
                "不，我也觉得脚步变轻了！",
                "嗯，我也觉得脚步变轻了！"
            ]
        },
        {
            "name": "唯独爱你",
            "text": "哈哈哈！\n那还是一起走路吧！"
        },
        {
            "name": "唯独爱你",
            "text": "我回来了～♡\n其实时间过得意外地快呢。"
        },
        {
            "name": "独白",
            "text": "虽然实际上是走了两个多小时，\n终于赶上了火车……\n但感觉却像一瞬间就到了终点。",
            "choice_data_list": [
                "多亏了你我才这么开心",
                "多亏了你我才这么开心",
                "有爱就能做到一切！",
                "有爱就能做到一切！",
                "还想再度过这样的时光",
                "还想再度过这样的时光"
            ]
        },
        {
            "name": "独白",
            "text": "虽然实际上是走了两个多小时，\n终于赶上了火车……\n但感觉却像一瞬间就到了终点。",
            "choice_data_list": [
                "多亏了你我才这么开心",
                "多亏了你我才这么开心",
                "有爱就能做到一切！",
                "有爱就能做到一切！",
                "还想再度过这样的时光",
                "还想再度过这样的时光"
            ]
        },
        {
            "name": "唯独爱你",
            "text": "我也一样哦！　多亏了训练员君，\n我真的很开心♪"
        },
        {
            "name": "唯独爱你",
            "text": "我也一样哦！　多亏了训练员酱，\n我真的很开心♪"
        },
        {
            "name": "唯独爱你",
            "text": "彼此因为对方，\n总是那么开心，那么幸福。\n这才是真正的爱♡　不是吗！",
            "choice_data_list": [
                "是啊！",
                "是啊！"
            ]
        },
        {
            "name": "独白",
            "text": "这是让我深切体会到\n相互付出、被爱的联结与力量的时光。"
        },
        {
            "name": "唯独爱你",
            "text": "没错，这就是爱啊！"
        },
        {
            "name": "唯独爱你",
            "text": "爱，就是肯定对方的存在。\n有时给予推动，成为彼此前进的动力。"
        },
        {
            "name": "唯独爱你",
            "text": "那是我一直都能从粉丝们身上感受到的东西——"
        },
        {
            "name": "唯独爱你",
            "text": "如果训练员君也能感受到，\n我会非常开心！"
        },
        {
            "name": "唯独爱你",
            "text": "如果训练员酱也能感受到，\n我会非常开心！"
        },
        {
            "name": "独白",
            "text": "平凡、质朴，却能感受到满满爱意、\n富足的时光。\n我要好好珍惜这份珍贵。"
        },
        {
            "name": "唯独爱你",
            "text": "——呵呵，我也是一样的心情。\n不过……"
        },
        {
            "name": "唯独爱你",
            "text": "不只是今天哦。\n无论什么时候……每天都是。"
        },
        {
            "name": "唯独爱你",
            "text": "无论何时，和训练员君一起的时光，\n我都觉得很幸福。"
        },
        {
            "name": "唯独爱你",
            "text": "无论何时，和训练员酱一起的时光，\n我都觉得很幸福。"
        }
    ]
}