{
    "no_wrap": true,
    "title": "樱花赏之后・盛开的爱",
    "text_block_list": [
        {
            "name": "实况",
            "text": "——现在进入决胜关键时刻！！\n接下来大家会如何出招呢！！"
        },
        {
            "name": "放声欢呼",
            "text": "就是现在！！！"
        },
        {
            "name": "实况",
            "text": "放声欢呼率先发起进攻！！\n放声欢呼——"
        },
        {
            "name": "唯独爱你",
            "text": "不会让你得逞！！！！！"
        },
        {
            "name": "唯独爱你",
            "text": "———哈啊啊啊啊啊！！！！"
        },
        {
            "name": "放声欢呼",
            "text": "什么……！？"
        },
        {
            "name": "实况",
            "text": "唯独爱你冲上来了！！\n唯独爱你加速了！！"
        },
        {
            "name": "实况",
            "text": "领先的是唯独爱你！！\n唯独爱你冲线了！！"
        },
        {
            "name": "实况",
            "text": "今年的樱花对爱微笑了！！\n冠军是唯独爱你！！！"
        },
        {
            "name": "唯独爱你",
            "text": "———我……我做到了……！"
        },
        {
            "name": "唯独爱你",
            "text": "我赢了……！！"
        },
        {
            "name": "观众A",
            "text": "哇啊啊啊！\n唯独爱你太强啦～～！！\n今年的后冠赛马娘也太厉害了吧……！！"
        },
        {
            "name": "观众B",
            "text": "放声欢呼也很厉害呢……！\n好期待『橡树大赛』啊……！！"
        },
        {
            "name": "三天打鱼系少女",
            "text": "太感动了……！　眼泪停不下来……！！\n唯爱酱……！\n真的变得好优秀了……！"
        },
        {
            "name": "社群成员们",
            "text": "『来了！！』『太好了！！！』\n『看到唯爱酱的奔跑了吗！』『恭喜！！！』\n『活着真好』『太棒了——！』"
        },
        {
            "name": "欢呼声",
            "text": "（哇啊啊啊啊啊啊啊啊啊！！！！）"
        },
        {
            "name": "放声欢呼",
            "text": "———唯爱酱！！"
        },
        {
            "name": "唯独爱你",
            "text": "放声酱……！"
        },
        {
            "name": "放声欢呼",
            "text": "首先，恭喜你！！"
        },
        {
            "name": "放声欢呼",
            "text": "虽然要先说恭喜——"
        },
        {
            "name": "放声欢呼",
            "text": "但我真的真的真的非常不甘心！！！"
        },
        {
            "name": "放声欢呼",
            "text": "明明能够跑出130英里级优秀的成绩的——！！"
        },
        {
            "name": "唯独爱你",
            "text": "放声酱……——"
        },
        {
            "name": "唯独爱你",
            "text": "（……放声酱其实还没有意识到）"
        },
        {
            "name": "唯独爱你",
            "text": "（今天的比赛……\n说实话，我觉得自己是运气好）"
        },
        {
            "name": "唯独爱你",
            "text": "（因为，其他参赛赛马娘的跑法，\n都刚好对我很有利……\n但对放声酱来说却完全相反）"
        },
        {
            "name": "唯独爱你",
            "text": "（如果再来一次，绝对不会像今天这样。\n要是跑十次，有九次都会输给她……\n放声酱真的很强）"
        },
        {
            "name": "唯独爱你",
            "text": "（——但今天赢的是我。\n好运站在我这边，也证明了我所锻炼的爱。\n所以……我要自信地面对她）"
        },
        {
            "name": "唯独爱你",
            "text": "（这就是，我对放声酱的爱）"
        },
        {
            "name": "放声欢呼",
            "text": "——……我决定了！！"
        },
        {
            "name": "放声欢呼",
            "text": "我决定不参加『橡树大赛』了！！"
        },
        {
            "name": "唯独爱你",
            "text": "诶……！？"
        },
        {
            "name": "放声欢呼",
            "text": "因为我在最擅长的距离上都输了。\n照现在这样的话，在『橡树大赛』上\n也不可能赢过唯爱酱……！"
        },
        {
            "name": "放声欢呼",
            "text": "我要……我要更加！\n继续磨炼我的短距离能力！！"
        },
        {
            "name": "放声欢呼",
            "text": "下次一定！\n我要在短距离上赢过唯爱酱！！"
        },
        {
            "name": "唯独爱你",
            "text": "……放声酱啊，你真是一如既往，\n永远都是这样呢。"
        },
        {
            "name": "唯独爱你",
            "text": "（我也不会只满足于今天的胜利。\n一定要让自己的跑法变得更强……！）"
        },
        {
            "name": "唯独爱你",
            "text": "我一定会再次迎接挑战。\n放声酱的短距离赛，我会用我的奔跑来回应。"
        },
        {
            "name": "放声欢呼",
            "text": "嗯，约定好了……！"
        },
        {
            "name": "创世驹",
            "text": "——……唯爱酱也好，放声酱也好，\n都远远超出了我的预想。"
        },
        {
            "name": "创世驹",
            "text": "我要……我要更加磨炼自己。\n我的『创世法则』……！"
        },
        {
            "name": "唯独爱你",
            "text": "——训练员君！",
            "choice_data_list": [
                "唯爱！恭喜你！！"
            ]
        },
        {
            "name": "唯独爱你",
            "text": "——训练员酱！",
            "choice_data_list": [
                "唯爱！恭喜你！！"
            ]
        },
        {
            "name": "唯独爱你",
            "text": "嗯……！\n这是我们努力绽放的樱花啊……！！"
        },
        {
            "name": "唯独爱你",
            "text": "是你把我带到这里来的……\n谢谢你，训练员君！",
            "choice_data_list": [
                "这句话应该我来说才对……！"
            ]
        },
        {
            "name": "唯独爱你",
            "text": "是你把我带到这里来的……\n谢谢你，训练员酱！",
            "choice_data_list": [
                "这句话应该我来说才对……！"
            ]
        },
        {
            "name": "独白",
            "text": "让自己负责的赛马娘获得经典赛的胜利，\n那是训练员无法不去梦想的荣耀。"
        },
        {
            "name": "独白",
            "text": "唯独爱你用充满爱的奔跑，\n实现了这个梦想。\n作为训练员，没有比这更开心的事了。"
        },
        {
            "name": "唯独爱你",
            "text": "呵呵……♡\n这样我们也算是彼此献上了爱呢。"
        },
        {
            "name": "唯独爱你",
            "text": "走吧！\n要让社群成员们见证我们的英姿！",
            "choice_data_list": [
                "嗯！",
                "好！"
            ]
        },
        {
            "name": "独白",
            "text": "就这样，与唯独爱你并肩，\n沐浴在为她喝彩的欢呼声中——"
        },
        {
            "name": "独白",
            "text": "我在心中默默发誓，\n一定还会再把这份荣耀带给唯独爱你。"
        },
        {
            "name": "独白",
            "text": "……『橡树大赛』马上就要来了。\n新的橡树女王，\n仿佛已经等不及要诞生了——"
        }
    ]
}