{
    "text_block_list": [
        {
            "name": "天狼星象征",
            "text": "哟，高峰。\n就这样一直呆站在这种地方真的好吗？"
        },
        {
            "name": "目白高峰",
            "text": "哎呀，有什么问题吗？"
        },
        {
            "name": "天狼星象征",
            "text": "不，只是目白家的那群家伙\n一直在到处找你。"
        },
        {
            "name": "目白高峰",
            "text": "是吗。不知道是有什么事呢。"
        },
        {
            "name": "天狼星象征",
            "text": "据那帮家伙说，今天是你的生日吧。"
        },
        {
            "name": "目白高峰",
            "text": "……啊，被你这么一说，确实如此。\n既然这样，那我就失礼了。"
        },
        {
            "name": "天狼星象征",
            "text": "要回去了？"
        },
        {
            "name": "目白高峰",
            "text": "不。"
        },
        {
            "name": "目白高峰",
            "text": "——我要让他们来追我。"
        },
        {
            "name": "天狼星象征",
            "text": "……哼，我还真同情那帮家伙啊。"
        },
        {
            "name": "目白高峰",
            "text": "呵呵。你还挺温柔的呢？"
        },
        {
            "name": "天狼星象征",
            "text": "谁知道呢。我现在可是打算\n抢在那帮家伙的前头呢。"
        },
        {
            "name": "目白高峰",
            "text": "……还真是热烈啊。\n在被你融化之前，我得赶紧逃走才行。"
        }
    ]
}