{
    "text_block_list": [
        {
            "name": "森林宝穴",
            "text": "茶座！！生日快乐啊！！\n既然这样，咱们来开个生日派对吧～！！"
        },
        {
            "name": "曼城茶座",
            "text": "……谢谢你。\n有这份心意，我就心满意足了……。"
        },
        {
            "name": "森林宝穴",
            "text": "说什么呢，别这么冷淡嘛。\n我都已经准备好了！\n难得过生日，咱们热热闹闹地庆祝一下吧！！"
        },
        {
            "name": "曼城茶座",
            "text": "不用了……热闹的庆祝方式我有点受不了……。\n所以您的好意我心领了……。"
        },
        {
            "name": "森林宝穴",
            "text": "哎呀真是的，我说的热热闹闹也就是那种……\n随口一说的气氛，或者是夸张点的说法啦！"
        },
        {
            "name": "森林宝穴",
            "text": "后山那儿有个风景很赞的地方哦。\n白天挺暖和的，吹着风也舒服。\n咱们去那儿喝杯茶怎么样？"
        },
        {
            "name": "曼城茶座",
            "text": "……！"
        },
        {
            "name": "森林宝穴",
            "text": "吃的我也准备了！还有感觉和咖啡\n挺搭的饼干什么的！呐，意下如何？"
        },
        {
            "name": "曼城茶座",
            "text": "……谢谢。如果您是这么打算的，\n那我就恭敬不如从命了……。"
        },
        {
            "name": "森林宝穴",
            "text": "哟西，那就这么定了！\n那咱们走吧！我也把速子那家伙叫上了！"
        },
        {
            "name": "曼城茶座",
            "text": "——请等一下。\n我可以收回前言，重新考虑一下吗……？"
        }
    ]
}