{
    "text_block_list": [
        {
            "name": "东海帝王",
            "text": "摄辉，生快——♪"
        },
        {
            "name": "东海帝王",
            "text": "呐，呐，你要去吃的吧，“凯撒芭菲”！\n我已经好好预订过了！"
        },
        {
            "name": "也文摄辉",
            "text": "非常感谢。\n那名为“皇帝”的芭菲究竟是何种滋味呢，\n我一直都在期待着这阵风的到来。"
        },
        {
            "name": "东海帝王",
            "text": "我也是，我也是！毕竟叫作“皇帝”嘛！\n肯定会是非常特别的芭菲！"
        },
        {
            "name": "东海帝王",
            "text": "比起可爱的风格，肯定更偏向帅气的风格吧！\n又时尚，感觉还很高档？\n说不定上面还会放个王冠之类的呢～！"
        },
        {
            "name": "也文摄辉",
            "text": "所谓“皇帝”的威严与高洁，\n竟然想将其凝聚在一盘之中——那股雄风，\n我也必须要全身心地去领略才行。"
        },
        {
            "name": "也文摄辉",
            "text": "……帝王同学。"
        },
        {
            "name": "也文摄辉",
            "text": "再次感谢你带来的这阵邀约凉风。"
        },
        {
            "name": "也文摄辉",
            "text": "如果只有我一个人的话，就算听闻了它的名字，\n大概也不会产生想要御风而行的动力吧。"
        },
        {
            "name": "也文摄辉",
            "text": "这份如春之疾风般的心意，\n成了对我来说最开心的礼物。"
        },
        {
            "name": "东海帝王",
            "text": "哪有啦！因为当我听到“凯撒芭菲”这个名字时，\n我就觉得，绝对要和摄辉一起去吃才行嘛♪"
        },
        {
            "name": "东海帝王",
            "text": "所以说，走吧，摄辉！\n让我们两个人一起把“皇帝”给攻略掉♪"
        },
        {
            "name": "也文摄辉",
            "text": "嗯。就让我们乘着友谊之风出发吧。"
        }
    ]
}