{
    "no_wrap": true,
    "title": "皋月赏结束后・厄运",
    "text_block_list": [
        {
            "name": "实况",
            "text": "选手们从第四弯道进入直线！"
        },
        {
            "name": "里见光钻",
            "text": "（──这里！从这里……！）"
        },
        {
            "name": "里见光钻",
            "text": "咦……？"
        },
        {
            "name": "里见光钻",
            "text": "（脚感觉……好沉重……！\n我应该要从这里开始加速才对的……！！）"
        },
        {
            "name": "里见光钻",
            "text": "唔唔唔唔唔啊啊啊啊啊……！"
        },
        {
            "name": "实况",
            "text": "……众所瞩目的里见光钻\n没能戴上“皋月赏”的荣冠！！"
        },
        {
            "name": "里见光钻",
            "text": "呼、呼……呼、呼……"
        },
        {
            "name": "观众A",
            "text": "啊～失败了啊。\n里见光钻表现得不如我的预期啊。"
        },
        {
            "name": "观众B",
            "text": "最后还看起来很辛苦的样子。\n照这样看来，长距离她应该是不行了……？",
            "choice_data_list": [
                "（那并不是她最佳的状态……）"
            ]
        },
        {
            "name": "独白",
            "text": "我从她比赛中的表现察觉到异状。\n比赛进入最后阶段的时候，\n里见光钻露出了明显的疲态。"
        },
        {
            "name": "独白",
            "text": "我想是因为……\n比赛前一路跑到赛场的关系，\n消耗了她不少的体力吧……？"
        },
        {
            "name": "独白",
            "text": "当时不跑的话，一定赶不上比赛。\n虽然那也是逼不得已的状况……"
        },
        {
            "name": "里见光钻",
            "text": "（……光是跑完2000米就觉得到极限了……\n这种表现怎么可能跑第一……）"
        },
        {
            "name": "里见光钻",
            "text": "（但是，要是我的实力再更坚强一点……！）"
        },
        {
            "name": "里见光钻",
            "text": "唔……！",
            "choice_data_list": [
                "（光钻……！）"
            ]
        },
        {
            "name": "里见光钻",
            "text": "……训练员……",
            "choice_data_list": [
                "害你要自己跑来赛场，我很抱歉",
                "害你要自己跑来赛场，我很抱歉"
            ]
        },
        {
            "name": "里见光钻",
            "text": "咦！？\n训练员不需要为这件事道歉呀！"
        },
        {
            "name": "里见光钻",
            "text": "当时的状况，\n我自己也觉得下车用跑的比较好！"
        },
        {
            "name": "里见光钻",
            "text": "……可是……刚好今天遇上了坏天气。\n才没能发挥100%的实力，\n最后输掉了比赛……"
        },
        {
            "name": "里见光钻",
            "text": "“里见家的赛马娘赢不了GⅠ”这个魔咒，\n我也……",
            "choice_data_list": [
                "光钻……"
            ]
        },
        {
            "name": "里见光钻",
            "text": "但我下一次不会再输了！"
        },
        {
            "name": "里见光钻",
            "text": "我一定会破除魔咒的！！"
        },
        {
            "name": "里见光钻",
            "text": "下一场“日本德比”！\n我一定会战胜魔咒，\n赢得胜利给大家看！！"
        },
        {
            "name": "独白",
            "text": "里见光钻强势地宣誓。\n因为这些运气不好的经历，\n反而更激发她想要战胜魔咒的决心。"
        }
    ]
}