{
    "no_wrap": true,
    "title": "tutti：合上声音！",
    "text_block_list": [
        {
            "name": "多旺达",
            "text": "呼，吃得好饱！大家也都没问题吧？\n那么，在午休结束前——"
        },
        {
            "name": "多旺达",
            "text": "金镇之光，可以开始了哦！\n一个人练声就到此为止吧。"
        },
        {
            "name": "烈焰快驹",
            "text": "金镇之光酱，吃饭好快啊～……！\n感觉你几乎没怎么嚼就吞下去了，真的没事吗……？"
        },
        {
            "name": "金镇之光",
            "text": "没问题。大约十分钟前喉咙，五分钟前胸口\n都难受得想在地上打滚，但现在已经完全没事了。"
        },
        {
            "name": "多旺达",
            "text": "这不是没事吧，真是的！总之……\n离下午上课还有30分钟，能合练三四遍吗？"
        },
        {
            "name": "烈焰快驹",
            "text": "啊，不过！下午的比赛策略，多旺达酱你们班\n今天不是有小测吗？我们班上周就考过了……"
        },
        {
            "name": "多旺达",
            "text": "对、对哦！那我想要留10分钟复习下笔记……\n不过练习也很重要……毕竟比赛马上就要到了……！"
        },
        {
            "name": "凯斯奇迹",
            "text": "没关系的，多旺达。\n今天……只要合练一次就足够了。"
        },
        {
            "name": "凯斯奇迹",
            "text": "来吧，钢琴也准备好了。\n大家排好队。自信满满地——来唱一遍吧。"
        },
        {
            "name": "大家",
            "text": "『相遇又别离　轻轻道一声「再会」\n我们曾走过 此生不复的风景　在那条小小的归途』——"
        },
        {
            "name": "烈焰快驹",
            "text": "……——！！　刚才那一遍——"
        },
        {
            "name": "金镇之光",
            "text": "唱得太美了太美了，太棒了、耶——！！"
        },
        {
            "name": "多旺达",
            "text": "是啊……！！\n和之前唱的时候完全不一样……真的感受到了和声！"
        },
        {
            "name": "烈焰快驹",
            "text": "和声……确实！比起之前，自己的声音、大家的声音\n都听得更清楚了……真的有『合唱』的感觉了呢！"
        },
        {
            "name": "金镇之光",
            "text": "接下来只要完善就行了。直奔优胜。拿下旅行券。\n玩个痛快再来顿豪华海鲜大餐，回宿舍直接睡到天亮。"
        },
        {
            "name": "烈焰快驹",
            "text": "还没去就已经在说回来了……！？"
        },
        {
            "name": "菱钻奇宝",
            "text": "嗯嗯，进展很顺利～♪　多亏了凯酱\n带着大家做了那么多分声部练习呢，谢谢啦～。"
        },
        {
            "name": "凯斯奇迹",
            "text": "哪里哪里。奇酱提议的K歌也起了大作用。\n而且最重要的是，大家都这么努力，才能有现在的合唱。"
        },
        {
            "name": "凯斯奇迹",
            "text": "真的……多亏了大家，才有了这么棒的合唱。\n呵呵，好期待让孩子们听到啊……！"
        },
        {
            "name": "菱钻奇宝",
            "text": "……嗯。呵呵，是啊。"
        },
        {
            "name": "菱钻奇宝",
            "text": "对了，凯酱。\n——这周末，你有空吗？"
        },
        {
            "name": "菱钻奇宝",
            "text": "咦，新出的奶昔是从昨天开始的？还是蜜薯味！？　\n哇，那肯定超好喝的吧……——啊，对不起。现在还不能跑偏。"
        },
        {
            "name": "凯斯奇迹",
            "text": "没事，我没关系的……那个，奇酱？\n说起来，今天的目的地是……？"
        },
        {
            "name": "菱钻奇宝",
            "text": "嗯～……呵呵，暂时还要保密哦。\n来来，跟我走吧～。"
        },
        {
            "name": "凯斯奇迹",
            "text": "——诶，是来买衣服的吗？\n是为了合唱大赛……？"
        },
        {
            "name": "凯斯奇迹",
            "text": "不过之前大家讨论服装的时候……不是说为了不紧张，\n就穿平时的便服就好吗？"
        },
        {
            "name": "菱钻奇宝",
            "text": "对对。所以也不是要买什么特别正式的衣服，\n就是想买件新的秋装啦～差不多这种感觉。"
        },
        {
            "name": "菱钻奇宝",
            "text": "其实和之前说的不一样，穿平时的也没问题啦？\n但就是……突然很想买新衣服了。"
        },
        {
            "name": "菱钻奇宝",
            "text": "……但就是，突然很想买。\n怎么说呢——想留个纪念！"
        },
        {
            "name": "凯斯奇迹",
            "text": "纪念……？"
        },
        {
            "name": "菱钻奇宝",
            "text": "……上课、作业、训练，大家都很忙，\n但还是努力凑时间，大家一起加油。"
        },
        {
            "name": "菱钻奇宝",
            "text": "在空教室集合，大家一起合唱。\n一开始虽然乱七八糟，但慢慢地变得越来越好。"
        },
        {
            "name": "菱钻奇宝",
            "text": "休息日还一起去唱K……啊哈，\n有时候还会在家庭餐厅聊到很晚。"
        },
        {
            "name": "菱钻奇宝",
            "text": "这一切一切，都、都超级开心的！"
        },
        {
            "name": "凯斯奇迹",
            "text": "！　……奇酱——"
        },
        {
            "name": "菱钻奇宝",
            "text": "所以说，纪念也好，留个回忆也好，随便啦！\n来，一起买新秋装吧。"
        },
        {
            "name": "菱钻奇宝",
            "text": "至于和大家说的不一样这件事～……\n她们一定会原谅我们的！　大概！"
        },
        {
            "name": "菱钻奇宝",
            "text": "毕竟我们可是这次合唱队的\n发起成员嘛！就当是特权啦……！"
        },
        {
            "name": "凯斯奇迹",
            "text": "……呵呵，……啊哈哈！\n对——对啊，奇酱。"
        },
        {
            "name": "凯斯奇迹",
            "text": "到时候我也会一起道歉的。\n所以……我们俩一起去求原谅吧。"
        },
        {
            "name": "菱钻奇宝",
            "text": "这、这样真的可以吗……？\n呜哇～，不知不觉连发型都精心打理了……！"
        },
        {
            "name": "凯斯奇迹",
            "text": "哇……嗯！　很适合你，真的！\n和你温暖的气质也很搭——"
        },
        {
            "name": "凯斯奇迹",
            "text": "嗯，很棒。呵呵，没什么好低头害羞的哦？\n奇酱，真的很可爱。"
        },
        {
            "name": "菱钻奇宝",
            "text": "呃，…………呜，～～～～～！"
        },
        {
            "name": "菱钻奇宝",
            "text": "啊啊啊，够了够了！\n凯酱你总是这样……让我一个人害羞！"
        },
        {
            "name": "菱钻奇宝",
            "text": "而且，下一个该你了，凯酱！\n我的已经决定好了。来，快点快点！"
        },
        {
            "name": "凯斯奇迹",
            "text": "怎么样……？　啊哈哈……店员推荐的我全都照单全收了……"
        },
        {
            "name": "菱钻奇宝",
            "text": "…………嗯，好！"
        },
        {
            "name": "菱钻奇宝",
            "text": "很适合你！　可爱！　还有帅气！\n帽子和眼镜也很搭，感觉很新鲜……总之，很棒！"
        },
        {
            "name": "凯斯奇迹",
            "text": "诶，诶？　那个……奇酱？"
        },
        {
            "name": "菱钻奇宝",
            "text": "总之，真的很棒！　啊～，凯酱果然很棒！！\n难怪你一直都挺受欢迎的呢～！！"
        },
        {
            "name": "凯斯奇迹",
            "text": "………………好吧，投降。\n奇酱，这样我也会害羞的啦。"
        },
        {
            "name": "菱钻奇宝",
            "text": "哼哼～。这就是回礼啦。"
        },
        {
            "name": "菱钻奇宝",
            "text": "呼，赶上电车啦～！　要是错过了门禁就糟了……\n结果买完衣服还到处逛了好久呢～。"
        },
        {
            "name": "凯斯奇迹",
            "text": "呵呵，是啊。蜜薯奶昔你分了好多给我，\n谢谢你，奇酱。真的又甜又好喝……"
        },
        {
            "name": "菱钻奇宝",
            "text": "哪里哪里，主要是你陪我一起控制卡路里啦。\n……好了，衣服也都准备齐了！"
        },
        {
            "name": "菱钻奇宝",
            "text": "马上就要比赛了～！\n……好期待啊，凯酱。"
        },
        {
            "name": "凯斯奇迹",
            "text": "嗯！　大家一起——开开心心地唱吧。"
        }
    ]
}