{
    "no_wrap": true,
    "title": "皋月赏结束后・还没追上",
    "text_block_list": [
        {
            "name": "优秀素质",
            "text": "唉……\n她果然很强。"
        },
        {
            "name": "优秀素质",
            "text": "……明明这次是我拿手的距离啊。"
        },
        {
            "name": "优秀素质",
            "text": "但仍然是追不上帝王啊……"
        },
        {
            "name": "东海帝王",
            "text": "嘿嘿，我果然跑得很快！"
        },
        {
            "name": "东海帝王",
            "text": "不过还是远远比不上会长。\n而且……"
        },
        {
            "name": "东海帝王",
            "text": "我还要继续变得更快！\n我办得到……本帝王大人办得到！"
        },
        {
            "name": "东海帝王",
            "text": "立刻去准备下场比赛吧！\nGOGOGO──♪"
        },
        {
            "name": "优秀素质",
            "text": "……"
        },
        {
            "name": "优秀素质",
            "text": "真是的……\n她老是令人觉得自己被甩得好远。"
        }
    ]
}